<?xml version="1.0" encoding="UTF-8"?>
<beans xmlns="http://www.springframework.org/schema/beans"
       xmlns:xsi="http://www.w3.org/2001/XMLSchema-instance"
       xsi:schemaLocation="http://www.springframework.org/schema/beans
	http://www.springframework.org/schema/beans/spring-beans-2.5.xsd">

    <bean id="nexusConfig" class="com.youama.nexus.core.system.ServiceUtil"/>

    <bean id="hibernateProperties" class="org.springframework.beans.factory.config.PropertiesFactoryBean">
        <property name="properties">
            <props>
                <prop key="hibernate.dialect">#{nexusConfig.getDBDialect()}</prop>
                <prop key="hibernate.hbm2ddl.auto">#{nexusConfig.getDBCreation()}</prop>
                <prop key="hibernate.current_session_context_class">#{nexusConfig.getDBSessionContext()}</prop>
                <prop key="hibernate.show_sql">#{nexusConfig.getDBLog()}</prop>
                <prop key="hibernate.generate_statistics">true</prop>
            </props>
        </property>
    </bean>

    <bean id="hibernatePackageToScan" class="java.lang.String">
        <constructor-arg value="**.model" />
    </bean>

</beans>